statement_extractor/__init__.py
statement_extractor/canonicalization.py
statement_extractor/cli.py
statement_extractor/extractor.py
statement_extractor/gliner_extraction.py
statement_extractor/llm.py
statement_extractor/models.py
statement_extractor/predicate_comparer.py
statement_extractor/scoring.py
statement_extractor/data/default_predicates.json
statement_extractor/data/statement_taxonomy.json
statement_extractor/database/__init__.py
statement_extractor/database/embeddings.py
statement_extractor/database/hub.py
statement_extractor/database/models.py
statement_extractor/database/resolver.py
statement_extractor/database/store.py
statement_extractor/database/importers/__init__.py
statement_extractor/database/importers/companies_house.py
statement_extractor/database/importers/companies_house_officers.py
statement_extractor/database/importers/gleif.py
statement_extractor/database/importers/sec_edgar.py
statement_extractor/database/importers/sec_form4.py
statement_extractor/database/importers/wikidata.py
statement_extractor/database/importers/wikidata_dump.py
statement_extractor/database/importers/wikidata_people.py
statement_extractor/document/__init__.py
statement_extractor/document/chunker.py
statement_extractor/document/context.py
statement_extractor/document/deduplicator.py
statement_extractor/document/html_extractor.py
statement_extractor/document/loader.py
statement_extractor/document/pipeline.py
statement_extractor/document/summarizer.py
statement_extractor/models/__init__.py
statement_extractor/models/canonical.py
statement_extractor/models/document.py
statement_extractor/models/entity.py
statement_extractor/models/labels.py
statement_extractor/models/qualifiers.py
statement_extractor/models/statement.py
statement_extractor/pipeline/__init__.py
statement_extractor/pipeline/config.py
statement_extractor/pipeline/context.py
statement_extractor/pipeline/orchestrator.py
statement_extractor/pipeline/registry.py
statement_extractor/plugins/__init__.py
corp_extractor-0.9.3.dist-info/METADATA
corp_extractor-0.9.3.dist-info/WHEEL
corp_extractor-0.9.3.dist-info/entry_points.txt
corp_extractor-0.9.3.dist-info/RECORD
