Metadata-Version: 2.4
Name: corp-extractor
Version: 0.9.3
Summary: Extract structured entity and relationship information from text
Project-URL: Homepage, https://github.com/corp-o-rate/statement-extractor
Project-URL: Documentation, https://github.com/corp-o-rate/statement-extractor#readme
Project-URL: Repository, https://github.com/corp-o-rate/statement-extractor
Project-URL: Issues, https://github.com/corp-o-rate/statement-extractor/issues
Author-email: Corp-o-Rate <neil@corp-o-rate.com>
Maintainer-email: Corp-o-Rate <neil@corp-o-rate.com>
License: MIT
Keywords: diverse-beam-search,embeddings,entities,entity-linking,entity-resolution,gemma,information-extraction,knowledge-graph,nlp,semantic-parsing,statement-extraction,subject-predicate-object,t5gemma2,transformers,triples
Classifier: Development Status :: 4 - Beta
Classifier: Intended Audience :: Developers
Classifier: Intended Audience :: Science/Research
Classifier: License :: OSI Approved :: MIT License
Classifier: Operating System :: OS Independent
Classifier: Programming Language :: Python :: 3
Classifier: Programming Language :: Python :: 3.10
Classifier: Programming Language :: Python :: 3.11
Classifier: Programming Language :: Python :: 3.12
Classifier: Topic :: Scientific/Engineering :: Artificial Intelligence
Classifier: Topic :: Scientific/Engineering :: Information Analysis
Classifier: Topic :: Text Processing :: Linguistic
Requires-Python: >=3.10
Requires-Dist: accelerate>=1.12.0
Requires-Dist: beautifulsoup4>=4.12.0
Requires-Dist: click>=8.0.0
Requires-Dist: gguf>=0.17.1
Requires-Dist: gliner2
Requires-Dist: httpx>=0.25.0
Requires-Dist: huggingface-hub>=0.20.0
Requires-Dist: llama-cpp-python>=0.3.16
Requires-Dist: numpy>=1.24.0
Requires-Dist: pycountry>=24.6.1
Requires-Dist: pydantic>=2.0.0
Requires-Dist: pymupdf>=1.23.0
Requires-Dist: sentence-transformers>=2.2.0
Requires-Dist: sqlite-vec>=0.1.6
Requires-Dist: torch>=2.0.0
Requires-Dist: transformers>=5.0.0rc3
Provides-Extra: all
Requires-Dist: llama-cpp-python>=0.2.0; extra == 'all'
Requires-Dist: pillow>=10.0.0; extra == 'all'
Requires-Dist: pytesseract>=0.3.10; extra == 'all'
Provides-Extra: dev
Requires-Dist: mypy>=1.0.0; extra == 'dev'
Requires-Dist: pytest-cov>=4.0.0; extra == 'dev'
Requires-Dist: pytest>=7.0.0; extra == 'dev'
Requires-Dist: ruff>=0.1.0; extra == 'dev'
Provides-Extra: llm
Requires-Dist: llama-cpp-python>=0.2.0; extra == 'llm'
Provides-Extra: ocr
Requires-Dist: pillow>=10.0.0; extra == 'ocr'
Requires-Dist: pytesseract>=0.3.10; extra == 'ocr'
